{
  "url": "https://x.com/PandaTalk8/status/2037317483884081443",
  "status": "success",
  "title": "KARPATHY 的 AUTORESEARCH：当 AI 开始自己做研究",
  "author": "PandaTalk8",
  "published_date": "2026-03-26",
  "folder_name": "PandaTalk8_KARPATHY_的_AUTORESEARCH：当_AI_开始自己做研究_2037317483884081",
  "local_path": "PandaTalk8_KARPATHY_的_AUTORESEARCH：当_AI_开始自己做研究_2037317483884081/PandaTalk8_KARPATHY_的_AUTORESEARCH：当_AI_开始自己做研究_2037317483884081.html",
  "timestamp": "2026-03-28T06:00:17.798828",
  "failure_reason": "",
  "source": "cli"
}