{
  "url": "https://x.com/i/status/2047925423187911062",
  "status": "success",
  "title": "科普：什么是永久投资组合？\n\n年化收益做到8%，适合普通人的无脑投资组合。\n\n非常简单的投资策略。\n\n从实操角度来说，\n\n算普通人友好。\n\n策略的名字叫永久投资组合。\n\n是一个叫哈利布朗的大叔，\n\n在",
  "author": "DtDt666",
  "published_date": "2026-04-25",
  "folder_name": "DtDt666_科普：什么是永久投资组合？年化收益做到8%，适合普通人的无脑投资组合。非_2047925423187911062",
  "local_path": "DtDt666_科普：什么是永久投资组合？年化收益做到8%，适合普通人的无脑投资组合。非_2047925423187911062/DtDt666_科普：什么是永久投资组合？年化收益做到8%，适合普通人的无脑投资组合。非_2047925423187911062.html",
  "timestamp": "2026-04-29T12:00:27.911349",
  "failure_reason": "",
  "source": "cli"
}