{
  "url": "https://x.com/beefnoode/status/2037008547310166060",
  "status": "success",
  "title": "Dan Koe 最新长文：怎样把创造力提升到一种近乎离谱的程度",
  "author": "beefnoode",
  "published_date": "2026-03-26",
  "folder_name": "beefnoode_Dan_Koe_最新长文：怎样把创造力提升到一种近乎离谱的程度_2037008547310166060_20",
  "local_path": "beefnoode_Dan_Koe_最新长文：怎样把创造力提升到一种近乎离谱的程度_2037008547310166060_20/beefnoode_Dan_Koe_最新长文：怎样把创造力提升到一种近乎离谱的程度_2037008547310166060_20.html",
  "timestamp": "2026-03-27T01:32:10.643872",
  "failure_reason": "",
  "source": "cli"
}